{
  "Data is not specified": "Data is not specified",
  "Enter the link to the avatar": "Enter the link to the avatar",
  "Enter the username": "Enter the username",
  "First and last name are required": "First and last name are required",
  "Gorod": "Gorod",
  "Incorrect age": "Incorrect age",
  "Invalid region": "Invalid region",
  "Oshibka pri zagruzke profilya": "Oshibka pri zagruzke profilya",
  "Otmenit": "Otmenit",
  "Poprobuite obnovit stranicu": "Poprobuite obnovit stranicu",
  "Profil": "Profil",
  "Redaktirovat": "Redaktirovat",
  "Server error when saving": "Server error when saving",
  "Sohranit": "Sohranit",
  "Ukazhite stranu": "Ukazhite stranu",
  "Ukazhite valytu": "Ukazhite valytu",
  "Vash vozrast": "Vash vozrast",
  "Vasha familiya": "Vasha familiya",
  "Vashe imya": "Vashe imya"
}
